pypsrp/__init__.py
pypsrp/_utils.py
pypsrp/client.py
pypsrp/complex_objects.py
pypsrp/encryption.py
pypsrp/exceptions.py
pypsrp/host.py
pypsrp/messages.py
pypsrp/negotiate.py
pypsrp/powershell.py
pypsrp/py.typed
pypsrp/serializer.py
pypsrp/shell.py
pypsrp/wsman.py
pypsrp/pwsh_scripts/__init__.py
pypsrp/pwsh_scripts/copy.ps1
pypsrp/pwsh_scripts/fetch.ps1
pypsrp-0.8.0.dist-info/LICENSE
pypsrp-0.8.0.dist-info/METADATA
pypsrp-0.8.0.dist-info/WHEEL
pypsrp-0.8.0.dist-info/top_level.txt
pypsrp-0.8.0.dist-info/zip-safe
pypsrp-0.8.0.dist-info/RECORD
