Metadata-Version: 2.1
Name: pypsrp
Version: 0.8.0
Summary: PowerShell Remoting Protocol and WinRM for Python
Home-page: https://github.com/jborean93/pypsrp
Author: Jordan Borean
Author-email: jborean93@gmail.com
License: MIT
Keywords: winrm,psrp,winrs,windows,powershell
Platform: UNKNOWN
Classifier: Development Status :: 4 - Beta
Classifier: License :: OSI Approved :: MIT License
Classifier: Programming Language :: Python :: 3
Classifier: Programming Language :: Python :: 3.6
Classifier: Programming Language :: Python :: 3.7
Classifier: Programming Language :: Python :: 3.8
Classifier: Programming Language :: Python :: 3.9
Classifier: Programming Language :: Python :: 3.10
License-File: LICENSE
Requires-Dist: cryptography
Requires-Dist: pyspnego (<1.0.0)
Requires-Dist: requests (>=2.9.1)
Provides-Extra: credssp
Requires-Dist: requests-credssp (>=1.0.0) ; extra == 'credssp'
Provides-Extra: kerberos
Requires-Dist: pyspnego[kerberos] ; extra == 'kerberos'
